semeval_8_2022_ia_downloader/__init__.py
semeval_8_2022_ia_downloader/check_downloaded.py
semeval_8_2022_ia_downloader/cli.py
semeval_8_2022_ia_downloader/semeval_8_2022_ia_downloader/__init__.py
semeval_8_2022_ia_downloader/semeval_8_2022_ia_downloader/items.py
semeval_8_2022_ia_downloader/semeval_8_2022_ia_downloader/middlewares.py
semeval_8_2022_ia_downloader/semeval_8_2022_ia_downloader/pipelines.py
semeval_8_2022_ia_downloader/semeval_8_2022_ia_downloader/settings.py
semeval_8_2022_ia_downloader/semeval_8_2022_ia_downloader/spiders/__init__.py
semeval_8_2022_ia_downloader/semeval_8_2022_ia_downloader/spiders/ia_article_spider.py
semeval_8_2022_ia_downloader-0.1.7.dist-info/LICENSE
semeval_8_2022_ia_downloader-0.1.7.dist-info/METADATA
semeval_8_2022_ia_downloader-0.1.7.dist-info/WHEEL
semeval_8_2022_ia_downloader-0.1.7.dist-info/entry_points.txt
semeval_8_2022_ia_downloader-0.1.7.dist-info/top_level.txt
semeval_8_2022_ia_downloader-0.1.7.dist-info/RECORD
