Metadata-Version: 2.1
Name: semeval-8-2022-ia-downloader
Version: 0.1.7
Summary: Script that scrapes news articles in the 2021 Semeval Task 8 format from the Internet Archive
Home-page: https://github.com/euagendas/semeval_8_2022_ia_downloader
Author: Mattia Samory
Author-email: mattia.samory@gesis.org
License: GNU General Public License v3
Keywords: semeval_8_2022_ia_downloader
Platform: UNKNOWN
Classifier: Development Status :: 2 - Pre-Alpha
Classifier: Intended Audience :: Developers
Classifier: License :: OSI Approved :: GNU General Public License v3 (GPLv3)
Classifier: Natural Language :: English
Classifier: Programming Language :: Python :: 3
Classifier: Programming Language :: Python :: 3.6
Classifier: Programming Language :: Python :: 3.7
Classifier: Programming Language :: Python :: 3.8
Requires-Python: >=3.6
License-File: LICENSE
Requires-Dist: setuptools (~=57.4.0)
Requires-Dist: pandas (~=1.3.1)
Requires-Dist: Scrapy (~=2.5.0)
Requires-Dist: itemadapter (~=0.3.0)
Requires-Dist: newspaper3k (~=0.2.8)
Requires-Dist: scrapy-wayback-machine (~=1.0.3)
Requires-Dist: requests (~=2.26.0)
Requires-Dist: tqdm (~=4.61.2)
